.DS_Store
source/__init__.py
source/logger_color.py
source/logger_config.py
source/logger_decorator.py
source/logger_maker.py
source/logger_method.py
source/logger_rf.py
source/logger_setting.py
source/logger_utility.py
bestlogger-1.0.0.dist-info/METADATA
bestlogger-1.0.0.dist-info/WHEEL
bestlogger-1.0.0.dist-info/top_level.txt
bestlogger-1.0.0.dist-info/RECORD
