Metadata-Version: 2.1
Name: bestlogger
Version: 1.0.0
Summary: this is a Better logger modules
Home-page: UNKNOWN
Author: wenlizhe
Author-email: UNKNOWN
License: UNKNOWN
Platform: UNKNOWN
